keepdelta/__init__.py
keepdelta/check.py
keepdelta/config.py
keepdelta/main.py
keepdelta/py.typed
keepdelta/types/__init__.py
keepdelta/types/collections.py
keepdelta/types/primitives/__init__.py
keepdelta/types/primitives/delta_bool.py
keepdelta/types/primitives/delta_complex.py
keepdelta/types/primitives/delta_float.py
keepdelta/types/primitives/delta_int.py
keepdelta/types/primitives/delta_str.py
keepdelta-0.2.0.dist-info/licenses/LICENSE
keepdelta-0.2.0.dist-info/METADATA
keepdelta-0.2.0.dist-info/WHEEL
keepdelta-0.2.0.dist-info/top_level.txt
keepdelta-0.2.0.dist-info/RECORD
