Metadata-Version: 2.4
Name: keepdelta
Version: 0.2.0
Summary: A Python Library for Human-Readable Data Differencing
Author-email: Aslan Noorghasemi <aslann@cmu.edu>, Christopher McComb <ccm@cmu.edu>
License: MIT
Classifier: Programming Language :: Python :: 3
Classifier: License :: OSI Approved :: MIT License
Classifier: Operating System :: OS Independent
Classifier: Topic :: Software Development :: Libraries :: Python Modules
Classifier: Topic :: Scientific/Engineering :: Information Analysis
Classifier: Typing :: Typed
Requires-Python: >=3.7
License-File: LICENSE
Dynamic: license-file
